pyplume/__init__.py
pyplume/figures.py
pyplume/mech.py
pyplume/model.py
pyplume/output.py
pyplume/statistics.py
pyplume/mechanisms/gri30.cti
pyplume/mechanisms/h2o2.cti
pyplume/mechanisms/test.cti
pyplume/originals/gri30.cti
pyplume/originals/h2o2.cti
pyplume/originals/test.cti
pyplume/tests/__init__.py
pyplume/tests/gri30.cti
pyplume/tests/testFigures.py
pyplume/tests/testMechs.py
pyplume/tests/testModel.py
pyplume/tests/testOutput.py
pyplume/tests/testStatistics.py
pyplume-0.0.6.dist-info/LICENSE
pyplume-0.0.6.dist-info/METADATA
pyplume-0.0.6.dist-info/WHEEL
pyplume-0.0.6.dist-info/entry_points.txt
pyplume-0.0.6.dist-info/top_level.txt
pyplume-0.0.6.dist-info/RECORD
