Metadata-Version: 2.1
Name: pyplume
Version: 0.0.6
Summary: This package contains files to build models for exhaust plume analysis and methods to analyze the results.
Home-page: https://github.com/SoftwareDevEngResearch/plume-generation-and-analysis
Author: Anthony Walker
Author-email: walkanth@oregonstate.edu
License: BSD 3-clause "New" or "Revised License"
Platform: UNKNOWN
Classifier: Programming Language :: Python :: 3
Classifier: License :: OSI Approved :: BSD License
Classifier: Operating System :: OS Independent
Requires-Python: >=3.6
Requires-Dist: pytest
Requires-Dist: cantera
Requires-Dist: h5py
Requires-Dist: matplotlib
Requires-Dist: numpy
